__init__.py
load.py
run.py
testsolar_python_unittest/__init__.py
testsolar_python_unittest/collector.py
testsolar_python_unittest/executor.py
python_unittest-0.2.16.dist-info/METADATA
python_unittest-0.2.16.dist-info/WHEEL
python_unittest-0.2.16.dist-info/top_level.txt
python_unittest-0.2.16.dist-info/RECORD
