Metadata-Version: 2.4
Name: python_unittest
Version: 0.2.16
Summary: Python unittest test tool for TestSolar
Author-email: dzx-cptbtptp <371140679@qq.com>
License: MIT
Requires-Python: >=3.9
Requires-Dist: testsolar-testtool-sdk>=0.4.2
Requires-Dist: pydantic>=2.7.4
Requires-Dist: loguru>=0.7.2
Requires-Dist: unittest-xml-reporting>=3.2.0
Requires-Dist: coverage>=7.6.1
